yaaat/__init__.py
yaaat/__main__.py
yaaat/changepoint_annotator.py
yaaat/harmonic_annotator.py
yaaat/harmonic_learner.py
yaaat/harmonic_stacker.py
yaaat/main.py
yaaat/nonlinear_annotator.py
yaaat/peak_annotator.py
yaaat/sequence_annotator.py
yaaat/utils.py
yaaat/images/changepoint_annotator_screenshot.jpg
yaaat/images/harmonic_annotator_screenshot.jpg
yaaat/images/lasso_screenshot.odt
yaaat/images/peak_annotator_screenshot.jpg
yaaat/test_files/test_audio/sequences/jelatik/0611.wav
yaaat/test_files/test_audio/sequences/jelatik/1311.wav
yaaat/test_files/test_audio/sequences/jelatik/1411.wav
yaaat/test_files/test_audio/sequences/jelatik/1511.wav
yaaat/test_files/test_audio/sequences/jelatik/1611.wav
yaaat/test_files/test_audio/sequences/jelatik/1713.wav
yaaat/test_files/test_audio/sequences/jelatik/1811.wav
yaaat/test_files/test_audio/sequences/jelatik/1911.wav
yaaat/test_files/test_audio/sequences/jelatik/2051.wav
yaaat/test_files/test_audio/sequences/jelatik/2111.wav
yaaat/test_files/test_audio/sequences/jelatik/2211.wav
yaaat/test_files/test_audio/sequences/jelatik/2411.wav
yaaat/test_files/test_audio/sequences/jelatik/2511.wav
yaaat/test_files/test_audio/syllables/jelatik/slice_1.wav
yaaat/test_files/test_audio/syllables/jelatik/slice_10.wav
yaaat/test_files/test_audio/syllables/jelatik/slice_2.wav
yaaat/test_files/test_audio/syllables/jelatik/slice_3.wav
yaaat/test_files/test_audio/syllables/jelatik/slice_4.wav
yaaat/test_files/test_audio/syllables/jelatik/slice_5.wav
yaaat/test_files/test_audio/syllables/jelatik/slice_6.wav
yaaat/test_files/test_audio/syllables/jelatik/slice_7.wav
yaaat/test_files/test_audio/syllables/jelatik/slice_8.wav
yaaat/test_files/test_audio/syllables/jelatik/slice_9.wav
yaaat/test_files/test_audio/syllables/kiwi/slice_1.wav
yaaat/test_files/test_audio/syllables/kiwi/slice_10.wav
yaaat/test_files/test_audio/syllables/kiwi/slice_2.wav
yaaat/test_files/test_audio/syllables/kiwi/slice_3.wav
yaaat-0.1.11.dist-info/licenses/LICENSE
yaaat-0.1.11.dist-info/METADATA
yaaat-0.1.11.dist-info/WHEEL
yaaat-0.1.11.dist-info/entry_points.txt
yaaat-0.1.11.dist-info/top_level.txt
yaaat-0.1.11.dist-info/RECORD
